home_ops_cli/__init__.py
home_ops_cli/aws/__init__.py
home_ops_cli/aws/fetch_aws_ips.py
home_ops_cli/aws/s3_manager.py
home_ops_cli/exceptions.py
home_ops_cli/github/__init__.py
home_ops_cli/github/delete_workflow_runs.py
home_ops_cli/kubernetes/__init__.py
home_ops_cli/kubernetes/wait.py
home_ops_cli/kubevirt/__init__.py
home_ops_cli/kubevirt/manager/__init__.py
home_ops_cli/kubevirt/manager/manager.py
home_ops_cli/kubevirt/manager/textual_app.py
home_ops_cli/kubevirt/vmexport/__init__.py
home_ops_cli/kubevirt/vmexport/download.py
home_ops_cli/main.py
home_ops_cli/options.py
home_ops_cli/talos/__init__.py
home_ops_cli/talos/regen_talosconfig.py
home_ops_cli/utils.py
home_ops_cli/vault/__init__.py
home_ops_cli/vault/backup_raft_snapshot.py
home_ops_cli/vault/bootstrap.py
home_ops_cli/vault/login.py
home_ops_cli/vault/pki/__init__.py
home_ops_cli/vault/pki/rotate_issuing.py
home_ops_cli/vault/restore_raft_snapshot.py
home_ops_cli/version.py
home_ops_cli-0.4.2.dist-info/METADATA
home_ops_cli-0.4.2.dist-info/WHEEL
home_ops_cli-0.4.2.dist-info/entry_points.txt
home_ops_cli-0.4.2.dist-info/licenses/LICENSE
home_ops_cli-0.4.2.dist-info/RECORD
