Metadata-Version: 2.4
Name: home-ops-cli
Version: 0.4.2
Summary: A CLI tool for managing home operations tasks.
License: MIT
License-File: LICENSE
Author: d4rkfella
Author-email: georgi.panov@darkfellanetwork.com
Requires-Python: >=3.13,<4.0
Classifier: License :: OSI Approved :: MIT License
Classifier: Programming Language :: Python :: 3
Classifier: Programming Language :: Python :: 3.13
Classifier: Programming Language :: Python :: 3.14
Requires-Dist: aiofiles (==25.1.0)
Requires-Dist: aiogzip (==1.1.0)
Requires-Dist: aiohttp (==3.13.2)
Requires-Dist: boto3 (==1.42.19)
Requires-Dist: botocore[crt]
Requires-Dist: hvac (==2.4.0)
Requires-Dist: inquirer (==3.4.1)
Requires-Dist: kr8s (==0.20.14)
Requires-Dist: kubernetes-asyncio (==33.3.0)
Requires-Dist: kubevirt-py (==1.7.0)
Requires-Dist: pyusb (==1.3.1)
Requires-Dist: ruamel.yaml (==0.18.17)
Requires-Dist: textual (==6.11.0)
Requires-Dist: textual-speedups (==0.2.1)
Requires-Dist: typer (==0.21.0)
Requires-Dist: validators (==0.35.0)
